trck/__init__.py
trck/update.py
trck-0.0.0.dist-info/METADATA
trck-0.0.0.dist-info/WHEEL
trck-0.0.0.dist-info/RECORD
