Metadata-Version: 2.3
Name: trck
Version: 0.0.0
Summary: Automate Time Track Google Sheet
Author-email: Mahdi Mir <imahdimir@gmail.com>
Requires-Dist: pandas
